README.md
setup.py
volley/__init__.py
volley/exceptions.py
volley/fields.py
volley/form.py
volley/validators.py
volley.egg-info/PKG-INFO
volley.egg-info/SOURCES.txt
volley.egg-info/dependency_links.txt
volley.egg-info/not-zip-safe
volley.egg-info/requires.txt
volley.egg-info/top_level.txt