Metadata-Version: 1.0
Name: volley
Version: 0.1
Summary: Python Data Validation Library
Home-page: https://www.github.com/yashpatel-itilite/volley
Author: UNKNOWN
Author-email: UNKNOWN
License: MIT
Platform: UNKNOWN
